easy_pysy/__init__.py
easy_pysy/core/__init__.py
easy_pysy/core/cli.py
easy_pysy/core/environment.py
easy_pysy/core/event.py
easy_pysy/core/lifecycle.py
easy_pysy/core/logging.py
easy_pysy/core/provider.py
easy_pysy/core/signal.py
easy_pysy/core/thread.py
easy_pysy/plugins/__init__.py
easy_pysy/plugins/api.py
easy_pysy/plugins/loop.py
easy_pysy/utils/__init__.py
easy_pysy/utils/common.py
easy_pysy/utils/decorators.py
easy_pysy/utils/functional/__init__.py
easy_pysy/utils/functional/dictionary.py
easy_pysy/utils/functional/function.py
easy_pysy/utils/functional/iterable.py
easy_pysy/utils/generators.py
easy_pysy/utils/inspect.py
easy_pysy/utils/json.py
easy_pysy/utils/markdown.py
easy_pysy/utils/model.py
easy_pysy/utils/object.py
easy_pysy-0.1.8.dist-info/METADATA
easy_pysy-0.1.8.dist-info/WHEEL
easy_pysy-0.1.8.dist-info/RECORD
