Metadata-Version: 2.1
Name: easy-pysy
Version: 0.1.8
Summary: 
Author: Pierre Merienne
Author-email: pierre.merienne@gmail.com
Requires-Python: ==3.9.2
Classifier: Programming Language :: Python :: 3
Requires-Dist: fastapi (>=0.85.0,<0.86.0)
Requires-Dist: loguru (>=0.6.0,<0.7.0)
Requires-Dist: pendulum (>=2.1.2,<3.0.0)
Requires-Dist: requests (>=2.28.0,<3.0.0)
Requires-Dist: toml (>=0.10.2,<0.11.0)
Requires-Dist: typer (>=0.6.1,<0.7.0)
Requires-Dist: uvicorn[standard] (>=0.18.3,<0.19.0)
